py_AHTx0/__init__.py
py_AHTx0-0.1.2.dist-info/LICENSE
py_AHTx0-0.1.2.dist-info/METADATA
py_AHTx0-0.1.2.dist-info/WHEEL
py_AHTx0-0.1.2.dist-info/top_level.txt
py_AHTx0-0.1.2.dist-info/RECORD
